Workbook

Sheet Bets
A1: Date | B1: Event | C1: Selection | D1: Type | E1: Target | F1: Fill | G1: Stake $ | H1: Result | I1: P&L $ | J1: CLV raw | K1: CLV no-vig | L1: Anchor | M1: Process | N1: Notes
A2: 2026-07-29 | B2: Full 5-game slate | C2: No bet - all 10 sides -EV | D2: pass | G2: 0 | H2: validated | I2: 0 | L2: clean | M2: worked | N2: Favorites went 2-3; both most-likely sides blew 6+ run leads; every listed price was -EV vs fair (avg -3.3%). Passing saved money.
A3: 2026-07-29 | B3: BAL @ DET | C3: Tigers ML | D3: order_unfilled | E3: 1.633 | G3: 0 | H3: no fill | I3: 0 | L3: clean | M3: worked | N3: Line closed 1.56-1.59, moving away; discipline held. Tigers lost 9-10 in 12 - a chased fill would have lost.
A4: 2026-07-30 | B4: CHC @ STL | C4: Cubs ML | D4: ticket | E4: 1.991 | F4: 1.99 | G4: 30000 | H4: won | I4: 29700 | J4: -0.005 | K4: -0.0513 | L4: conflict | M4: miss | N4: Cashed on variance: close (CHC +100/STL -120, sharp money on STL) says the edge was not there. Fair missed the no-vig close by 3.7pts on a source-conflict market -> conflict-refusal rule shipped.
A5: 2026-07-30 | B5: PIT @ CIN | C5: Reds ML | D5: order_unfilled | E5: 1.985 | G5: 0 | H5: no fill | I5: 0 | L5: clean | M5: pending | N5: Game pending at grading. Skenes scratched late (bullpen game) - the priced premise changed; listed-pitcher rules would have mattered.
A6: 2026-07-30 | B6: CHC @ STL | C6: Cross-source 'arb' +1.28% | D6: flag | G6: 0 | H6: validated | I6: 0 | L6: conflict | M6: worked | N6: Labeled unverified staleness and not executed; the close proved it was quote drift, not free money.
A7: 2026-07-31 | B7: NYY @ CHC | C7: Market refused (conflict rule) | D7: refusal | G7: 0 | H7: validated | I7: 0 | L7: conflict | M7: worked | N7: Close CHC -140 landed on the sportsbook consensus; Polymarket 52c was the stale outlier (NYY won 2-0 as a +130 dog - vs the close that bet was -7% EV luck). Refusal correct.
A8: 2026-07-31 | B8: PHI @ BAL | C8: Phillies ML | D8: order_open | E8: 2.097 | G8: 0 | H8: no fill | I8: 0 | L8: clean | M8: worked | N8: PHI never traded above 2.06 (target 2.10). Close no-vig PHI 0.467: even at target the bet was -2% vs close - not filling saved money. SportsGrid model lean (PHI 54%) was the wrong side per the close.
A9: 2026-07-31 | B9: PIT @ CIN | C9: Pirates ML | D9: order_open | E9: 1.966 | G9: 0 | H9: no fill | I9: 0 | L9: clean | M9: worked | N9: PIT -120 to -136 all day, never near the 1.966 target. Close no-vig PIT 0.564: a 1.966 fill would have been ~+11% EV vs close - right side, market never paid the price.
A10: 2026-08-01 | B10: PIT @ CIN | C10: Reds ML | D10: order_unfilled | E10: 2.231 | G10: 0 | H10: no fill | I10: 0 | L10: clean | M10: worked | N10: CIN never traded above +106 (2.06) - 17 cents short of the 2.231 bar; the '+120 one source' quote was never corroborated. CIN lost 1-4, so no fill dodged a loss; vs the no-vig close a 2.231 fill would still have been +EV (right side, market never paid).
A11: 2026-08-01 | B11: PIT @ CIN | C11: Pirates ML | D11: order_open | E11: 1.888 | G11: 0 | H11: superseded | I11: 0 | L11: clean | M11: superseded | N11: Superseded by the full-card re-rank (PIT side fell out of the top orders).
A12: 2026-08-01 | B12: NYY @ CHC | C12: Market refused (conflict rule, day 2) | D12: refusal | G12: 0 | H12: validated | I12: 0 | L12: conflict | M12: worked | N12: Refusal correct, with a twist: the close landed NYY road-favorite (-122 to -132; CHC +102/+105) - the OPPOSITE of our 'books CHC 1.62' quote, which no closing book corroborates. That quote was stale/wrong (flagged for provenance). Polymarket NYY 54c was actually the consensus side. CHC won 5-2 anyway - neither side's value story survived. Conflict rule worked for the right reason: garbage inputs were refused, not priced.
A13: 2026-08-01 | B13: WSH @ ATL | C13: Market refused (no anchor >= 0.5) | D13: refusal | G13: 0 | H13: validated | I13: 0 | L13: clean | M13: worked | N13: Braves 8-3. Polymarket-only board stayed unpriced per the 0.45-sharpness demotion; no book close collected for this game.
A14: 2026-08-01 | B14: PHI @ BAL | C14: Orioles ML | D14: order_unfilled | E14: 2.225 | G14: 0 | H14: no fill | I14: 0 | L14: clean | M14: worked | N14: Fill ambiguous: consensus close +119 (2.19) never reached the 2.225 bar, but SportsGrid reported 'BAL +125 at other books' pregame, which would have filled. Graded no-fill on the consensus board we price from. BAL lost 0-5, so neither grading forfeits a win; a phantom fill would have lost. Single-book-anchor caveat from pre-registration stands.
A15: 2026-08-01 | B15: SEA @ POR (MLS) | C15: Timbers ML | D15: order_unfilled | E15: 2.23 | G15: 0 | H15: no fill | I15: 0 | L15: clean | M15: worked | N15: NO BET - user report (the only fill oracle; pages 403 post-hoc): the prediction-market ask had moved above the 45c stand-down line (engine minimum 2.23) by bet time, so per the slip's own fill rule the order did not fire. Paper grade of the 2.273 listed snapshot: Portland won 2-1 and the number beat the bet365 close 2.05/3.80/3.00 by +10.9% raw / +4.5% no-vig - the edge was real at the snapshot, and it decayed before execution. Standing down was correct: at the moved ask the +2.5% EV bar was no longer met.
A16: 2026-08-02 | B16: WSH @ ATL | C16: Braves ML | D16: order_void | E16: 1.866 | G16: 0 | H16: no fill | I16: 0 | L16: clean | M16: miss | N16: VOID - PROCESS MISS (user report): the card shipped hours after this game's 1:35 PM ET first pitch. The container clock read Sunday evening; I overrode it because search snippets showed no Sunday finals - but a lagging search index is not pre-game proof. Order was never actionable; no bet placed, none should be. Original order terms preserved above for the record; outcome deliberately NOT graded (no hindsight grading of a void order).
A17: 2026-08-02 | B17: BOS @ LAD (Sunday Night Baseball) | C17: Dodgers ML | D17: order_void | E17: 1.666 | G17: 0 | H17: no fill | I17: 0 | L17: clean | M17: miss | N17: VOID - cancelled at 7:03 PM ET with first pitch 7:20 PM ET: no time to re-verify the line, and every price on the card is a morning-stale snapshot. An unsupervisable order is not an order.
A18: 2026-08-02 | B18: MIA @ NYM | C18: Marlins ML | D18: order_void | E18: 1.925 | G18: 0 | H18: no fill | I18: 0 | L18: clean | M18: miss | N18: VOID - shipped after the 1:40 PM ET first pitch (same process miss as the headline order). No bet placed, none should be.
A19: 2026-08-02 | B19: PIT @ CIN | C19: Moneyline refused (conflict rule) | D19: refusal | G19: 0 | H19: validated | I19: 0 | L19: conflict | M19: worked | N19: Refusal validated on PROCESS: the book-vs-Polymarket gap (CIN 1.676 vs 55c) never visibly converged before first pitch - the market stayed unpriceable by our rule at every observable snapshot. CIN won 10-2 (Burns 6 IP 9 K) and the close landed -148, but outcome isn't the verdict; the conflict rule is now 4-for-4 on process. Pre-registered under the conflict rule, graded at the close.
A20: 2026-08-03 | B20: STL @ NYY (7:05 PM ET Mon) | C20: Yankees ML | D20: order_unfilled | E20: 1.599 | G20: 0 | H20: no fill | I20: 0 | L20: clean | M20: worked | N20: NOT FILLED - and saved by it. Every dated Monday price moved AWAY from the 1.599 trigger (NYY -186 Sunday -> -195/-210/-217/-235 across books at close); then NYY lost 7-13 (Burleson 3 HR off Schlittler). Our fair (64.1%) sat above a close (~65%) that the result embarrassed - calibration fine, outcome brutal, order discipline kept the stake at zero.
A21: 2026-08-03 | B21: SEA @ NYL (7:00 PM ET Mon) | C21: Liberty ML | D21: order_filled_paper | E21: 1.278 | F21: 1.278 | G21: 0 | H21: won | I21: 0 | J21: -0.0318 | K21: -0.0536 | L21: clean | M21: flagged | N21: FILL CONDITION MET AND CASHED - but read the CLV. Liberty drifted -450 -> -315 close, straight through the 1.278 trigger, and won 95-83. At the conservative fill (1.278) that is NEGATIVE CLV vs the ~1.35 no-vig close: a resting limit order fills precisely when the market moves through it - adverse selection (Walters: the drift was information; the market said the Storm were live-r than our day-old board). Paper grade only, stake 0: this was a backup order, not the headline, and the user bets headline only.
A22: 2026-08-03 | B22: SFG @ TEX (8:05 PM ET Mon) | C22: Rangers ML | D22: order_unfilled | E22: 2.03 | G22: 0 | H22: no fill | I22: 0 | L22: clean | M22: worked | N22: NOT FILLED - TEX never reached plus-money (observed -105 to -125 across books; +103 trigger unreached), then lost 1-5 with five errors behind Webb's 6 shutout IP. Second unfilled loser dodged on the day.
A23: 2026-08-03 | B23: SDP @ AZ (9:40 PM ET Mon) | C23: Board rejected pre-slate (garbled quotes) | D23: flag | G23: 0 | H23: validated | I23: 0 | L23: conflict | M23: worked | N23: Rejection fully validated: the real Monday market was near pick'em with ARI a slight HOME favorite (BetMGM/DK SDP -102 / ARI -118; Yahoo -113) - the garbled 'SD -185/ARI +737' board was wrong on side AND magnitude. ARI won 5-1. Garbage in, nothing out: correct.
A24: 2026-08-06 | B24: ATH @ CIN (start time unverified; typical 12:35 PM ET getaway) | C24: Reds ML | D24: order_unfilled | E24: 1.679 | G24: 0 | H24: no fill | I24: 0 | L24: clean | M24: worked | N24: NOT FILLED: CIN drifted our way (-171 open -> -158 at first pitch) but never reached the -147 (1.679) bar; best documented 1.633. CIN won 6-5, and a 1.679 fill would have carried +2.8% raw CLV vs the close - right side, right price demand, market never paid it. Reverse line movement toward the road dog noted pregame; the bar held anyway.
A25: 2026-08-06 | B25: Dinamo Minsk @ Braga (UECL Q3 leg 1; kickoff ~3:00-3:45 PM ET assumed) | C25: Braga ML (3-way, draw/away lose) | D25: order_unfilled | E25: 1.141 | G25: 0 | H25: no fill | I25: 0 | L25: clean | M25: worked | N25: NOT FILLED: Braga sat 1.10-1.11 everywhere pre-match; the 1.141 re-verified quote never existed. Braga won 1-0. The demotion logic validated exactly: on extreme favorites the only 'fills' available are cross-book noise, and even that noise stayed under 4 cents.
A26: 2026-08-06 | B26: ARI @ CAR, Hall of Fame Game (8:00 PM ET Thu, Canton - neutral site) | C26: Cardinals +1.5 | D26: order_unfilled | E26: 1.88 | G26: 0 | H26: no fill | I26: 0 | L26: clean | M26: worked | N26: NOT FILLED by one cent of juice: ARI +1.5 reached ~-115 game-day vs the -114 bar - and then LOST (CAR won by exactly 3 on the final play). The near-miss dodged a loser; fill discipline is net positive on the card (two would-have-won fills never reached target, the one would-have-lost fill missed by a cent).
A27: 2026-08-06 | B27: ARI @ CAR (HOF Game) | C27: Wong teaser leg suppressed (ARI +1.5 -> +7.5) | D27: flag | G27: 0 | H27: validated | I27: 0 | L27: clean | M27: worked | N27: Suppression validated on process with an ironic outcome: the suppressed leg (ARI +1.5 -> +7.5) would have back-doored a win (lost by 3), but the game produced 63 points against a 34.5 total - preseason margins have NO key-number structure, which is precisely why the leg had no business existing. Note-only; engine gating change still deferred (Walters rule).
A28: 2026-08-10 | B28: NYM @ ATL (7:15 PM ET Mon) | C28: Braves ML | D28: order_filled | E28: 1.684 | F28: 1.684 | G28: 0 | H28: lost | I28: 0 | J28: -0.0152 | K28: -0.0305 | L28: clean | M28: flagged | N28: FILLED AND LOST - first filled headline order. The trigger (1.684/-147) verifiably printed at multiple books (-138 Covers, -140 FanDuel, -143 Caesars) before first pitch; ATL lost 8-5. Graded at the 1.684 floor: raw CLV -1.5%, no-vig -3.1% - NEGATIVE, the second straight drift-fill with negative CLV (Liberty Aug-3 was the first). The market drifted toward the Mets all day and the drift was information; re-priced at the drifted number, our own blend no longer cleared the bar. DRIFT-CANCEL RULE shipped to CLAUDE.md off this graded pair. User stake unconfirmed - tracker computes the loss at your unit stake; if you passed on it, tell me and I regrade to no-bet (Timbers precedent).
A29: 2026-08-10 | B29: Shnaider vs Swiatek, WTA Toronto QF (7:00 PM ET Mon) | C29: Swiatek ML | D29: order_unfilled | E29: 1.403 | G29: 0 | H29: no fill | I29: 0 | L29: clean | M29: worked | N29: NOT FILLED: no book ever printed 1.403+ (-285/-300 everywhere). Swiatek won 6-2 6-1 - a missed winner, which is the cost side of the same discipline that has dodged three losers. The bar cuts both ways; that is the design.
A30: 2026-08-10 | B30: COL @ AZ (Chase Field, evening - exact time TBC) | C30: Diamondbacks ML | D30: order_unfilled | E30: 1.624 | G30: 0 | H30: no fill | I30: 0 | L30: clean | M30: worked | N30: NOT FILLED: line moved AWAY from the order all day (-179 -> -190s; the -164 outlier board never reached -160). Game in progress at grading - outcome irrelevant to an unfilled order.
A31: 2026-08-10 | B31: KC @ LAD (10:10 PM ET Mon - Skubal home debut) | C31: Moneyline refused (conflict rule) | D31: refusal | G31: 0 | H31: validated | I31: 0 | L31: conflict | M31: worked | N31: VALIDATED, with the sharpest twist yet: the definitive Monday close was LAD -325/-330 (FanDuel + 'other oddsmakers' + Polymarket 74c all agree near 76%) - the -160 board we saw was itself a stale/erroneous print. The conflict was real, and this time the BOOK leg was the garbage and the prediction market was near truth (mirror of the Aug-1 stale 'CHC 1.62'). The rule doesn't care which source lies - it refuses the disagreement. LAD needed a 7th-inning rally to win 6-5. 7-for-7 on refusals/flags.
A32: 2026-08-11 | B32: CLE @ DET (6:40 PM ET Tue, Comerica) | C32: Tigers ML | D32: order_unfilled | E32: 2.164 | G32: 0 | H32: no fill | I32: 0 | L32: clean | M32: worked | N32: NOT FILLED - the market ran the other way, hard: DET +113 Monday night -> -120/-121 favorite at first pitch. No +116 ever printed. DET won 6-4, so another would-have-won missed - but the swing's SIZE is the lesson: an overnight board can embed a different starting pitcher than game-day reality (Drew Anderson started). Listed-pitcher rule: every future order names its assumed starters, and a change voids the premise (Skenes-scratch lesson, Jul 30, finally codified).
A33: 2026-08-11 | B33: TB @ ATH (9:40 PM ET Tue) | C33: Rays ML | D33: order_unfilled | E33: 1.72 | G33: 0 | H33: no fill | I33: 0 | L33: clean | M33: worked | N33: NOT FILLED - TB shortened -146 -> -180 and won 12-4. Fourth straight unfilled order whose side won. Tempting to call the bar too high; the ledger says otherwise - the only two orders that DID fill both carried negative CLV and went 1-1. Unfilled winners are the visible cost of refusing bad prices; filled losers are the invisible cost of chasing. No parameter change (Walters rule).
A34: 2026-08-11 | B34: KC @ LAD (10:10 PM ET Tue) | C34: Moneyline refused (conflict rule, day 2) | D34: refusal | G34: 0 | H34: validated | I34: 0 | L34: conflict | M34: worked | N34: Book LAD -285 vs Polymarket 72c: nearly agreeing today, but cross-source best prices still net -0.99% hold - the rule is binary and fires the same on small conflicts as wide ones (that binariness is the Cubs-3.7pt lesson). 6th application. Monday's refusal grades at its close next cycle alongside this one. || SETTLED: close LAD -275 (~70-71% no-vig) vs Polymarket 72c - the sources converged AT the close, meaning no exploitable edge ever existed. LAD won 5-4. Refusals now 8-for-8.
A35: 2026-08-12 | B35: NYM @ ATL (7:15 PM ET Wed; PITCHERS: Thornton vs Mahle) | C35: Braves ML | D35: order_unfilled | E35: 1.666 | G35: 0 | H35: no fill | I35: 0 | L35: clean | M35: worked | N35: NOT FILLED - the board moved the wrong way all day (-156 -> -158/-175 close); -150 never printed. ATL won 6-3: the FIFTH straight unfilled order whose side won. Pattern reading: our fairs are directionally right and the market agrees too fast to pay our price - which is what near-parity Brier with the close predicts. The bar stays (Walters rule); the edge has to come from being earlier, not looser.
A36: 2026-08-12 | B36: ATP Montreal SF: Jodar vs Nakashima (6:00 PM ET Wed) | C36: Nakashima ML | D36: order_filled_paper | E36: 2.969 | F36: 2.969 | G36: 0 | H36: won | I36: 0 | J36: 0.0099 | K36: -0.0173 | L36: clean | M36: worked | N36: FILL CONDITION MET VIA CROSS-BOOK SHOPPING - AND WON. +200 (>= the +197 trigger) was genuinely available at a book pre-match while Dimers' board showed +188; Nakashima won 7-6(3) 6-4. At the 2.969 floor vs the 2.94 close: raw CLV +1.0%, no-vig -1.7% - the first fill in this ledger with POSITIVE RAW CLV and the best fill-CLV recorded (prior fills: -5.4% and -3.1% no-vig), precisely because it came from price dispersion across books (allowed) rather than line drift (forbidden). The drift-vs-shopping distinction now has favorable evidence on the shopping side. Paper grade, stake 0 - backup order, user bets headline only.
A37: 2026-08-12 | B37: SEA @ NYY (7:05 PM ET Wed; PITCHERS: Miller vs Warren) | C37: Yankees ML | D37: order_unfilled | E37: 1.893 | G37: 0 | H37: no fill | I37: 0 | L37: clean | M37: worked | N37: NOT FILLED - opened -119 and firmed to -131; the -112 trigger never printed. NYY won 10-5 anyway (sixth unfilled winner if you count this one alongside the ATL streak).
A38: 2026-08-13 | B38: MIL @ LAD (10:10 PM ET Thu; PITCHERS: Drohan vs Sasaki) | C38: Brewers ML | D38: order_unfilled | E38: 2.353 | G38: 0 | H38: no fill | I38: 0 | L38: clean | M38: worked | N38: NOT FILLED - EdgeBets' 8-book closing recap tops MIL out at +129 (range +115/+129, consensus +123/+125); the +136 trigger never printed anywhere. Both listed pitchers started (Shane Drohan vs Sasaki) so the premise held; the price just never came. MIL won 5-4 on a 3-run 9th - the SEVENTH unfilled order whose side won. The bar stays (Walters rule): the two orders that ever DID fill via drift carried the ledger's worst CLV.
A39: 2026-08-13 | B39: PHI @ MIN, Field of Dreams (7:30 PM ET; Nola vs Bradley; RAIN RISK) | C39: Over 8.5 | D39: order_unfilled | E39: 1.937 | G39: 0 | H39: no fill | I39: 0 | L39: clean | M39: worked | N39: NOT FILLED - Over sat -118/-120 all day and never reached the -107 trigger. Game went UNDER (8 runs): the FIRST unfilled order whose side LOST, i.e. the bar's first visible counterfactual save (~$40 at quarter-Kelly). The unfilled-order ledger is now 7 winners, 1 loser - and the loser is the one the bar refused to pay for. First graded third-party total model (SportsLine 60.2% over): WRONG. Rain clause never triggered - played as scheduled.
A40: 2026-08-13 | B40: PHI @ MIN, Field of Dreams (same game) | C40: Phillies ML | D40: order_unfilled | E40: 2.063 | G40: 0 | H40: no fill | I40: 0 | L40: clean | M40: worked | N40: NOT FILLED - PHI ranged -102/-104 all day and closed ~-103 (SBR); the +106 trigger needed plus-money that never printed. PHI won 7-1 (Schwarber 2 HR) - the EIGHTH unfilled order graded, 7 of whose sides won.
A41: 2026-08-15 | B41: KC @ LAA (9:38 PM ET Sat; PITCHERS: Dobnak vs Detmers) | C41: Royals ML | D41: order_unfilled | E41: 2.465 | G41: 0 | H41: no fill | I41: 0 | L41: clean | M41: worked | N41: NOT FILLED - KC never evidenced past +135 (trigger +147) and Polymarket sat pinned at the 41c board price all day; no 40.5c ask printed. Fill oracle open: if your execution says otherwise, report and I regrade. COUNTERFACTUAL SAVE #2, and the biggest yet: KC was SHUT OUT 1-0 (Detmers 8 scoreless, 11 K). The closest-to-live order in ledger history would have lost at any fill price. Dobnak/Detmers premise held.
A42: 2026-08-15 | B42: SD @ CLE (7:10 PM ET Sat; ASSUMED pitchers Vasquez-SD vs Cantillo-CLE, side-assignment UNVERIFIED) | C42: Padres ML | D42: order_void | E42: 2.268 | G42: 0 | H42: void | I42: 0 | L42: clean | M42: worked | N42: VOID ON THE PREMISE CLAUSE, and unfilled anyway: San Diego ran a Wandy Peralta OPENER instead of listed probable Vasquez (Cantillo did start for CLE), and the written clause - 'void unless the pairing is confirmed at bet time' - fired exactly as designed. The price also ran away (+118 -> +105, never +127). SD lost 6-1: save #3 on the same card.
A43: 2026-08-15 | B43: STL @ CHC (2:20 PM ET Sat; PITCHERS: McGreevy vs Boyd) | C43: Cubs ML | D43: order_unfilled | E43: 1.673 | G43: 0 | H43: no fill | I43: 0 | L43: clean | M43: worked | N43: NOT FILLED - CHC shortened hard from -166 to -174/-185 closes; -149 never printed. McGreevy/Boyd started as listed - and Boyd (8-1) was tagged for three Baez HRs in an 8-4 loss. Save #4... third of THREE on this card alone. Every Saturday order's side lost; the bar refused all of them.
A44: 2026-08-15 | B44: MIL @ LAD rematch (7:15 PM ET Sat; Misiorowski vs TBD) | C44: no side - market refused | D44: refusal | G44: 0 | H44: resolved - anchor real | I44: 0 | L44: degraded | M44: flagged | N44: REFUSAL #9 (rule is 8-for-8 lifetime). Thursday's showdown rerun, now with MIL the AWAY FAVORITE at DK -142 while numberFire says LAD 52.9%, our log5 says LAD 53.0%, and Polymarket (MIL 53c) sides with the book. Best-price cross-hold LAD 2.18 book + MIL 53c PM = 98.9c round trip: negative hold on a 0.6-sharpness anchor = conflicting quotes, not an arb. Both prior KC@LAD refusals resolved as one side being a garbage print - we don't know which side is garbage here either, and that is exactly the point. || SETTLED, and this one is DIFFERENT from refusals 1-8: the DK -142 was REAL (market-wide close MIL -130/-142; Misiorowski 6 IP 1 R, MIL won 4-1). Polymarket 53c was not garbage either - it was LAGGING a sharp ace-driven move, which is what produced the negative cross-hold. First refusal triggered by genuine price dispersion rather than a garbage print - and the refused market contained the winning side at the dispersed price (MIL 53c). Also true: our in-house/numberFire LAD lean was flat wrong. Scoreboard: 8-for-8 catching garbage, 0-for-1 on lag. No rule change on n=1 (Walters); distinction logged.
A45: 2026-08-18 | B45: SEA @ MIL (7:40 PM ET Tue, American Family Field; PITCHERS: Miller vs Harrison) | C45: Brewers ML | D45: order_unfilled | E45: 1.761 | G45: 0 | H45: no fill | I45: 0 | L45: clean | M45: worked | N45: NOT FILLED - the trigger was -131 or better and the market moved the WRONG way from the first print: -148 early -> -150 open -> -159/-160/-165 -> -168 close. No book ever came within 17 cents of the trigger; no drift-through, so no re-price question. MIL then won 22-0, so the side won - but the close (61.6% no-vig) steamed PAST our 58.2% fair, meaning even a -148 take would have been the slow side of a sharp move our own model layer (60.7% MIL) partly anticipated. CORRECTED RUNNING TALLY of every order that never filled (incl. the voided SD premise): sides are now 9W-4L across 13 (Swiatek, CIN, DET, TB, ATL, NYY, MIL 8/13, PHI 8/13, MIL 8/18 won; FoD Over, KC, CHC, SD lost) - earlier notes' 7W counts undercounted by one, fixed here. Fill oracle stands: report an execution and I regrade.
A46: 2026-08-20 | B46: Mirassol @ LDU Quito, Libertadores R16 leg 2 (6:00 PM ET Thu, Quito, 2850m; agg 1-1) | C46: LDU Quito ML (3-way; draw/away lose) | D46: order_unfilled | E46: 1.682 | G46: 0 | H46: no fill | I46: 0 | L46: degraded | M46: worked | N46: NOT FILLED - no named book was ever pinned at 1.682+ (an unattributed ESPN-visible -145 = 1.690 existed but Pinnacle sat 1.55 simultaneously; the live-single-book-only condition was written for exactly this). COUNTERFACTUAL SAVE #5: the 90-min result was 0-0 - a fill would have LOST even as LDU advanced on penalties. Pricing lesson logged: the 1.60 averaged anchor sat between a 1.55 sharp and a 1.69 soft quote, so the order's 'edge' was partly anchor softness - averaged trios stay consensus-c and live-only forever. Never-filled sides: 9W-5L at this point in the pass.
A47: 2026-08-20 | B47: Dream @ Sparks, WNBA (10:00 PM ET Thu, Crypto.com Arena) | C47: Dream ML | D47: order_void | E47: 1.34 | G47: 0 | H47: void | I47: 0 | L47: degraded | M47: worked | N47: VOID ON THE PREMISE CLAUSE, pre-game and result-independent: Brionna Jones was ruled OUT for the Dream (left leg, third straight miss) on final injury reports dated to this game - the pre-registered condition 'void if B. Jones or Reese is OUT' fired exactly as written. (Reese played; the 'questionable' chatter traced to July articles and was discarded on date discipline.) Second premise-clause void in a week (SD Padres opener was the first) - the clause class is earning its keep. No stake, no fill, no grade.
A48: 2026-08-20 | B48: 49ers @ Chargers, NFL preseason Wk 2 (10:00 PM ET Thu, SoFi) | C48: 49ers ML | D48: order_unfilled | E48: 1.879 | G48: 0 | H48: no fill | I48: 0 | L48: clean | M48: worked | N48: NOT FILLED on post-ship evidence - SF only SHORTENED after our card (board 1.769 -> DK close 1.80... vs LAC flipping to dog the line moved through -118 to -125; an SF +102 quote exists but traces to early-week, pre-card). No post-ship 1.879+ at a named book evidenced; fill oracle open. SF won 41-17 - a would-have-won missed at the bar's usual price of discipline.
A49: 2026-08-21 | B49: America @ Juarez, Liga MX J5 (11:00 PM ET Fri, Estadio Olimpico Benito Juarez) | C49: Club America ML (3-way; draw/home lose) | D49: order_unfilled | E49: 1.945 | G49: 0 | H49: no fill | I49: 0 | L49: clean | M49: worked | N49: NOT FILLED - the 1.945 trigger sat above the ENTIRE market all day (best anywhere: a 1.85 aggregate leg; consensus close ~1.76-1.77) and the market shortened toward America, who won 2-1. A would-have-won at a price that never existed - the bar's usual cost. Our Codere 1.82 anchor graded honest (slightly above close); the scary Bet365 -241 capture from Friday night was a bad aggregator read, not the market.
A50: 2026-08-21 | B50: Coventry @ Arsenal, EPL opener (3:00 PM ET Fri, Emirates) | C50: Arsenal ML (3-way) | D50: order_unfilled | E50: 1.224 | G50: 0 | H50: no fill | I50: 0 | L50: clean | M50: worked | N50: NOT FILLED - best named-book price all day was DK -475 (1.211); the 1.224 trigger never printed (FanDuel closed -550). Arsenal won 3-0: a would-have-won that never offered the price. The extreme-favorite demotion was correct: the market's ceiling sat below our bar all day.
A51: 2026-08-21 | B51: Coventry @ Arsenal, same match - total 2.5 | C51: Over 2.5 | D51: order_unfilled | E51: 1.662 | G51: 0 | H51: no fill | I51: 0 | L51: clean | M51: worked | N51: NOT FILLED - Over 2.5 closed -176/-181 (1.552-1.568); the 1.662 trigger never evidenced. It landed (3 goals) and SportsLine's 64% graded RIGHT on its first EPL outing - a model note for the file, priced away by the market. Never-filled sides after this pass: 12W-5L across 17.
A52: 2026-08-21 | B52: Jets @ Steelers, NFL preseason Wk 2 (7:00 PM ET Fri, Acrisure) | C52: Jets ML | D52: order_filled_paper | E52: 1.804 | F52: 1.804 | G52: 0 | H52: won | I52: 0 | J52: -0.0088 | K52: -0.0479 | L52: degraded | M52: worked | N52: FILL CONDITION MET AT NAMED BOOKS - AND WON. The 'drift toward PIT' we flagged at ship was the OPENER (PIT -3, Jets 2.47); named books held Jets above the 1.804 trigger all day and DK closed Jets -122 (1.82). Jets won 17-0. Paper grade at the 1.804 floor: raw CLV -0.9%, no-vig -4.8% - roughly flat, because the conservative floor sits at the close; anything nearer the open was strongly positive. Second paper fill in ledger history; both cashed. Lesson: our unnamed-book preseason snapshot (1.70) was the soft side of a market that was never there - named-book conditions turn soft snapshots into real prices. Stake 0 - backup order, user bets headline only.
A53: 2026-08-22 | B53: Atlas @ Cruz Azul, Liga MX J5 (11:00 PM ET Sat, Estadio Banorte/Azteca) | C53: Cruz Azul ML (3-way; draw/away lose) | D53: order_unfilled | E53: 1.569 | G53: 0 | H53: no fill | I53: 0 | L53: clean | M53: worked | N53: STOOD DOWN PER DRIFT-CANCEL - and the rule saved the ticket. The board drifted from Caliente -205/Codere -200 THROUGH the 1.569 trigger (a Betway 1.62 shows on Aug-22 comparison pages, timing unverified; Dimers' -190 board does NOT clear). The slip's printed rule covers exactly this: a drift-through is a changed premise - re-price and stand down. The drift was the market fading Cruz Azul, and Cruz Azul lost 0-2 at home. CONDITIONAL SAVE #7 (the drift-taker loses). FILL ORACLE OPEN: if you actually took 1.62, report it and I regrade as a loss at your stake (Braves precedent). Drift-throughs are now 0-for-3 as bets (Liberty, Braves, this).
A54: 2026-08-22 | B54: Hernandez vs Rodrigues, UFC FN Sacramento main event (~10:15 PM ET walk) | C54: Hernandez ML | D54: order_unfilled | E54: 1.691 | G54: 0 | H54: no fill | I54: 0 | L54: clean | M54: worked | N54: NOT FILLED - the first UFC order's line steamed the wrong way all week (DK -166 -> Hard Rock -185 -> DK -198 close); -145 never existed. COUNTERFACTUAL SAVE #6: Rodrigues won the fight by UD at +164 - a fill would have lost. The steam was information, again.
A55: 2026-08-22 | B55: Hamilton @ Toronto, CFL Wk 12 (7:00 PM ET Sat, BMO Field) | C55: Argonauts ML | D55: order_unfilled | E55: 1.536 | G55: 0 | H55: no fill | I55: 0 | L55: degraded | M55: worked | N55: NOT FILLED - no named book ever better than -225 vs the -187 trigger (the unattributed -218 we demoted was close to true). Argos won 39-20, a would-have-won at a price that never existed. Note: the WEATHER CLAUSE actually TRIGGERED (thunderstorm-delayed start) - had anything filled, the printed clause voided it anyway. Clause class: 3-for-3 firing correctly when conditions hit.
A56: 2026-08-23 | B56: Boca Juniors @ Racing Club, Clausura fecha 6 (8:30 PM ET Sun, El Cilindro) | C56: Boca Juniors ML (3-way; draw/home lose) | D56: order_unfilled | E56: 2.767 | G56: 0 | H56: no fill | I56: 0 | L56: degraded | M56: worked | N56: NOT FILLED - no named book ever printed Boca near +177 (best found: bplay 2.60, Betsson 2.55, bet365 DNB 1.62 implying ~2.4-2.6); the trigger sat ~8% above the whole named market. COUNTERFACTUAL SAVE #7: the match ended 1-1, so any filled 90-minute ticket loses - and the draw-heavy H2H that set the high bar was exactly the risk that landed. Never-filled orders' sides now 14W-8L across 22.
A57: 2026-08-24 | B57: PIT @ SD (9:40 PM ET Mon, Petco; PITCHERS: Ashcraft vs Robbie Ray) | C57: Pirates ML | D57: ticket | E57: 2 | F57: 2 | G57: 35 | H57: won | I57: 35 | J57: 0.0477 | K57: 0 | L57: clean | M57: worked | N57: WON - the first tier bet cashes. PIT 3-2 in 12; $35 at 2.00 returns $70 (+$35 at the reference stake - report your actual book/price/stake and I restate real P&L). Ashcraft/Ray premise held; bet365 +100 documented at the latest pre-game snapshot. CLV at the split close: raw +4.8% vs the -110/-110 consensus, no-vig +0.0% (book range -3.3% to +1.3%) - we took the best price on the board and the market ended where we bet it. TIER SCOREBOARD: 1 settled, 1-0, mean no-vig CLV ~0.0%; 14 more to the pre-registered rollback checkpoint.
A58: 2026-08-24 | B58: PHI @ SEA (9:40 PM ET Mon, T-Mobile Park; Wheeler vs Gilbert) | C58: Phillies ML | D58: order_unfilled | E58: 1.927 | G58: 0 | H58: no fill | I58: 0 | L58: degraded | M58: worked | N58: STOOD DOWN PER DRIFT-CANCEL - SAVE #8. A named-book -108 print IS evidenced intraday (NBC/DK-network content), but it was a TRANSIENT CROSS: the board sat -115 below the trigger, touched -108, and closed back at -115/-118. Taxonomy now codified: a market STANDING above the trigger all day = legitimate fill (Jets precedent); a market that transiently CROSSES the trigger = drift-through, re-price and stand down (Liberty/Braves/Cruz Azul/this - drift-throughs now 0-for-4 as bets). PHI lost 2-9 (Wheeler 5-run 1st); a -108 fill was -1.6% no-vig CLV AND a full-stake loss. Fill oracle open: if you took -108, report it and I regrade.
A59: 2026-08-25 | B59: CHC @ AZ (9:40 PM ET Tue, Chase Field; Holmes vs Pfaadt) | C59: D-backs ML | D59: order_unfilled | E59: 2.005 | G59: 0 | H59: no fill | I59: 0 | L59: degraded | M59: worked | N59: STOOD DOWN PER DRIFT-CANCEL - and this one is the rule's first counterfactual MISS. DK printed AZ +101 (>= the 2.005 trigger) pre-game, but the board moved TOWARD the Cubs everywhere else (-105/-105 open -> BetMGM -110s, SI CHC -112): a drift-through, not a standing price. Re-priced at the drifted number the blend gave -0.15% - below the model bar - so the stand-down was rule-correct. AZ then won 5-4 on a walk-off. Drift-throughs as hypothetical bets: 1-for-5 (Liberty, Braves, Cruz Azul, PHI lost; this won). The rule keeps its job on the aggregate; the miss is logged, not hidden.
A60: 2026-08-25 | B60: WAS @ PHX (10:00 PM ET Tue, Footprint Center) | C60: Mystics ML | D60: order_unfilled | E60: 1.781 | G60: 0 | H60: no fill | I60: 0 | L60: degraded | M60: worked | N60: NOT FILLED - the only -128 print was an unnamed aggregator leg; named books ran -130/-135. The fires-only-at-named-books condition held. Mystics won 94-84: a would-have-won at a price never verified to exist. Never-filled sides: 16W-9L across 26 after this card.
A61: 2026-08-25 | B61: PIT @ SD (9:40 PM ET Tue, Petco; SKENES vs Michael King) | C61: Pirates ML | D61: order_filled_paper | E61: 2.028 | F61: 2.028 | G61: 0 | H61: won | I61: 0 | J61: 0.009 | K61: -0.0243 | L61: clean | M61: worked | N61: FILLED AT A STANDING CROSS-BOOK PRICE - AND WON. BetMGM's own game blog quoted PIT +105 (2.05 >= the 2.028 trigger) while the FanDuel anchor sat -104/-102: the Jets shape (standing-above, not a transient cross), so the fill is legitimate. PIT won 1-0 behind Skenes. Paper grade at the 2.028 floor: raw CLV +0.9%, no-vig -2.4%. numberFire's 55.8% lean graded RIGHT. Stake 0 - backup order, user bets headline only. TIER SCOREBOARD: 2 settled (Mon ticket + this), 2-0 on results, but no-vig CLV is Mon ~0.0% / this -2.4% - mean ~-1.2%, NEGATIVE. That is the pre-registered rollback metric: if it is still <0 at 15 settled, both tiers revert to 2.5%. 13 to the checkpoint.
A62: 2026-08-26 | B62: Brewers @ Mets, MLB (7:10 PM ET Wed, Citi Field) | C62: Brewers ML | D62: order_unfilled | E62: 1.69 | G62: 0 | H62: no fill | I62: 0 | L62: degraded | M62: worked | N62: NOT FILLED - the trigger price is not evidenced as ever standing. Best named-book MIL price found anywhere pre-game: DraftKings -149 (1.671), four cents short of the -145 trigger; BetRivers held -165 and no Polymarket ask at 59c or lower surfaced. MIL won 8-1 - a would-have-won at a price that never existed (never-filled sides now ~17W-9L across 27). Footnote that matters: Dustin May exited after ONE PITCH (comebacker off the scapula). A fill would have survived the premise (he started), but the win would have been carried entirely by Gasser's relief work - the listed-pitcher clause is doing real risk work even on nights it technically holds.
A63: 2026-08-26 | B63: Toluca vs Austin FC, Leagues Cup QF (8:30 PM ET Wed, Harrison NJ - neutral) | C63: none - market refused | D63: refusal | G63: 0 | H63: validated | I63: 0 | L63: conflict | M63: worked | N63: REFUSAL VALIDATED - and the conflict resolved toward the sportsbook, as our sharpness demotion assumes. An independent named pre-game trio surfaced post-hoc (Toluca -185 / +300 / +425) devigging to ~59.6% Toluca - 5 points from BetUS's 65%, 10 from Kalshi's 50c. Toluca won 2-0 IN THE 90 (Helinho pen 53', Diaz 90+7'; Austin down a man from 40'). One sample, but both the price check and the result say the exchange cents were the off number. The 15-point venue gap was real and unpriceable at bet time; refusing was the only correct position. Kept from the same card: Valkyries -909 (demoted) won by 25 - demotion cost nothing, as designed: it prices risk, not outcomes.
A64: 2026-08-28 | B64: Alouettes @ Blue Bombers, CFL Wk 13 (8:30 PM ET Fri, Princess Auto Stadium, Winnipeg) | C64: Blue Bombers ML (home dog) | D64: ticket | E64: 3.846 | F64: 3.846 | G64: 23 | H64: won | I64: 65.46 | J64: 0.1312 | K64: 0.0265 | L64: degraded | M64: worked | N64: WON 44-28 - the third tier ticket cashes, and this one BEAT THE CLOSE decisively: 26c entry vs a book close that held +240 (raw CLV +13.1%) and a no-vig fair of ~28.2% (no-vig CLV +2.7%) while the spread moved toward Montreal all day. $23 at 3.846 returned $88.46 (+$65.46 at the reference stake - report your actual venue/price/stake and I restate real P&L; Polymarket's indexed print held WPG 26c). The Timbers stand-down line never triggered. TIER SCOREBOARD: 3 settled, 3-0, no-vig CLVs 0.0% / -2.4% / +2.7% (power-devig no-vig, same method as the engine - the raw +13.1% shrinks because power devig assigns most of a longshot pair's juice to the dog) - mean +0.1%, positive for the first time but barely; 12 to the rollback checkpoint.
A65: 2026-08-28 | B65: Red Sox @ Yankees, MLB (7:05 PM ET Fri, Yankee Stadium) | C65: Yankees ML | D65: order_unfilled | E65: 1.721 | G65: 0 | H65: no fill | I65: 0 | L65: degraded | M65: worked | N65: NOT FILLED - no named book ever printed NYY -139 or better (evidenced range -148 to -173) and Polymarket stood at 59c (a Covers column even flagged taking NYY 'up to 59 cents' - consistent with our one-cent miss). NYY won 1-0: another would-have-won at a price that never existed. Never-filled sides ~18W-9L.
A66: 2026-08-28 | B66: Orioles @ Athletics, MLB (9:40 PM ET Fri, Sutter Health Park, West Sacramento) | C66: Athletics ML (home dog) | D66: order_unfilled | E66: 2.041 | G66: 0 | H66: no fill | I66: 0 | L66: degraded | M66: worked | N66: NOT FILLED - AND THE CONDITION SAVED A LOSS. Aggregator picks-tables printed ATH +119/+120, but no NAMED book was ever behind those numbers and FanDuel (the named board) sat +100, under the +104 trigger. The fires-only-on-a-named-book-print condition held - and ATH LOST 3-4 in 10 innings, so an aggregator-print fill would have been a full-stake loser. This is the named-book condition's cleanest save yet (distinct from the 8 drift-cancel saves). Never-filled sides ~18W-10L across 29.
A67: 2026-08-28 | B67: Dodgers @ Tigers, MLB (6:40 PM ET Fri, Comerica Park) - the Skubal marquee | C67: none - market refused | D67: refusal | G67: 0 | H67: validated | I67: 0 | L67: conflict | M67: worked | N67: CONFLICT REFUSAL on the game everyone wanted: Skubal's revenge start. Two named books agree (BetRivers -225, FanDuel -215, ~67-69% LAD) while Polymarket sells LAD at 64c on $112K of volume - a 4-6 point venue fight whose best-price synthetic hold is NEGATIVE (-1.29%). The rule (degraded + negative cross-hold = unpriceable, never an arb) is 4-for-4 lifetime and was validated 48h ago by Toluca. POLICY QUESTION PRE-REGISTERED, not acted on: this shape differs from past conflicts - BOTH named books agree and only the exchange is off, and the candidate bet (LAD at PM 64c) is AT the outlier venue in the DIRECTION of the anchor consensus (+5.0% EV if the books are right, -0.6% if PM is right - positive under any mixture). Settle must record which venue was right here AND in the other three refusals (HOU@NYM, SEA@TOR, TEX@MIL); if the books-agree-exchange-off subtype keeps grading book-side-right, that is the ledger evidence a refinement needs. No parameter moves tonight (Walters rule). || SETTLED: the gap was REAL and the BOOKS were the better venue. FanDuel closed ~-215/+180 (no-vig LAD ~65.7%) vs Polymarket's 63-64c - a genuine ~2-point cross-venue disagreement that never converged. LAD won 2-1 behind Skubal (6 IP, 1 R in his Comerica return; under 7.5 cashed - our registered under lean RIGHT). Policy-question tally opens: books-agree-exchange-off subtype 1-0 books. A PM-side LAD bet at 64c would have won and carried positive CLV vs the book close - logged as the cost side of the refusal, per the honesty standard.
A68: 2026-08-28 | B68: HOU@NYM, SEA@TOR, TEX@MIL - three more venue conflicts, one card | C68: none - markets refused | D68: refusal | G68: 0 | H68: graded | I68: 0 | L68: conflict | M68: worked | N68: Grouped refusal, engine-fired on all three: HOU@NYM (board HOU -128 vs Polymarket 51/50 pick'em on thin $59K - hold -0.70%), SEA@TOR (FanDuel -172 vs BET99 -155 one-sided - hold -0.45%; numberFire 53% TOR also far under the market), TEX@MIL (FanDuel -205 vs scoresandstats -181, 24 cents - hold -0.52%). Four refusals in one night is the dispersion mandate working as designed: hunting second venues finds gaps, and most gaps are somebody's bad quote, not value. Settle records the truth venue per game for the refusal-calibration ledger. || SETTLED, venue verdicts: TEX@MIL - FanDuel RIGHT (close clustered -190/-205; scoresandstats -181 was the stale outlier; MIL won 6-1). SEA@TOR - FanDuel RIGHT (close -161/-179 with FD dead-center; BET99 -155 sat outside the whole range; TOR won 8-1). HOU@NYM - THE EXCHANGE WAS RIGHT: the -128 board was stale and the market closed -105/-106, converging exactly to Polymarket's 51/50 (HOU won 3-1 - outcome noise; the close is the verdict). Running venue-calibration: named books 3, exchange 1 - and the exchange's win came against an unnamed consensus board, not against fresh named books. The sharpness hierarchy (named > consensus > exchange) survives the night.
A69: 2026-08-31 | B69: Phillies @ D-backs, MLB (9:40 PM ET Mon, Chase Field) | C69: D-backs ML (home dog) | D69: order_unfilled | E69: 2.085 | G69: 0 | H69: no fill | I69: 0 | L69: degraded | M69: worked | N69: NOT FILLED BY ONE CENT - AND THE CLAUSE SAVED A LOSER AGAIN. Best named-book print all day: DraftKings +108 (2.08), one cent under the +109 trigger; FanDuel +100, consensus +105/+106; a lone '+109' mention appears in a snippet that simultaneously says 'best odds +103' - no verified standing print. AZ then LOST 1-2 (Nola out-dueled Pfaadt), so a fill would have graded L at ~flat CLV vs the +105/+106 close. That is the second consecutive card where the named-book/one-cent discipline refused a bet that loses (Fri ATH, Mon AZ). numberFire's 52.9% AZ graded WRONG. Never-filled sides ~18W-11L across 30 - the bars keep refusing the right ones lately.
A70: 2026-09-01 | B70: Giants @ Pirates, MLB (6:40 PM ET Tue, PNC Park) - Skenes vs Webb | C70: Pirates ML | D70: order_unfilled | E70: 1.689 | G70: 0 | H70: no fill | I70: 0 | L70: degraded | M70: worked | N70: NOT FILLED - no named book ever printed PIT -145 or better; the dated band was -158 (Athlon) to -162 (Predictem/DK -161). PIT then won 13-12 on a walk-off THROWING ERROR after blowing a six-run lead with Skenes shelled for 5 - a would-have-won that would have spent nine innings looking like a loser. The resting-order design priced the fill, not the outcome; a fill at the trigger would have carried ~+4% raw CLV vs the -161 close, which is exactly why the trigger sits where it sits. Never-filled sides ~19W-11L across 31.
A71: 2026-09-01 | B71: Marlins @ Royals, MLB (7:40 PM ET Tue, Kauffman Stadium) | C71: none - market refused | D71: refusal | G71: 0 | H71: validated | I71: 0 | L71: conflict | M71: worked | N71: CONFLICT REFUSAL, engine-fired at -7.41% cross-hold: BetRivers prints KC -117 while YouWager prints MIA -160 - 50+ cents apart, the favorite FLIPS between boards. Per the post-phantom-anchor hierarchy (adopted after the MIL -196 grade), a conflict this size is encoded intact and refused, never resolved by hand - one of these boards is fiction and settle will record WHICH, feeding the calibration that already reads named-book > exchange > unnamed-article. DK splits (86% ML handle on KC) lean toward BetRivers being live, but handle is color, not truth. || SETTLED: KC closed the favorite at -117 (BetRivers) / -120 (DraftKings, sharps 66% bets / 88% dollars). The YouWager 'MIA -160' board was FICTION - a 40-cent inversion of the real market that appears only on that blog. Refusal validated on process; MIA won 6-3 as the +100 dog (outcome noise - the close is the verdict). Venue-truth ledger: named books 4, exchange 2, blog boards 0-for-3 this week.
A72: 2026-09-03 | B72: Colorado @ Georgia Tech, CFB Week 1 (8:00 PM ET Thu, Bobby Dodd Stadium, ESPN) | C72: Colorado ML (road dog) | D72: order_unfilled | E72: 3.23 | G72: 0 | H72: no fill | I72: 0 | L72: degraded | M72: worked | N72: NOT FILLED BY THREE CENTS - AND THE SIDE WON 14-13. Best named print all day: DraftKings +220 (3.20) against the +223 (3.23) trigger; FanDuel and bet365 +205; the unnamed +240 was the pre-ship opener. The market moved TOWARD Colorado all day on sharp money (DK: 10% of tickets / 63% of handle), which is why the trigger - set 1.5% above a blended fair that weights the market 0.85 - drifted out of reach instead of into it. Colorado won on a TD with 0:42 left and a blocked field goal. The ledger's first CFB order: a missed winner, honestly logged. Never-filled sides ~20W-11L across 32.
A73: 2026-09-04 | B73: Pachuca @ FC Juarez, Liga MX Apertura J7 (11:00 PM ET Fri, Estadio Olimpico Benito Juarez) | C73: Pachuca to win in 90 minutes (draw loses) | D73: ticket | E73: 2.174 | F73: 2.174 | G73: 104 | H73: won | I73: 122.1 | J73: 0.1137 | K73: 0 | L73: degraded | M73: worked | N73: WON - Pachuca 2-0 at Juarez, the fourth tier ticket and the second sourced from an exchange. $104 at 2.174 returns $226.10 (+$122.10 at the reference stake - report your actual venue, price and size and I restate real P&L). SETTLEMENT PREMISE CONFIRMED INDEPENDENTLY: Robinhood's listing of the same contract words it '90 minutes plus stoppage, excluding extra time and penalties' - exactly the market we priced, and both goals came in regulation, so there was no ambiguity. The 46c ask was corroborated as a real quoted price by a second source ('Kalshi has Pachuca at 46%'), though NO volume or depth figure is indexed anywhere - fill size remains unverified by anything but your own report. CLV IS GENUINELY AMBIGUOUS and is recorded conservatively. Raw +11.4%% against the ESPN BET board we anchored on, which re-indexed unchanged at 1.952. But that page serves a single untimestamped snapshot, and a second dated board had Pachuca LENGTHENING to +102 while Juarez shortened - implying a closing Pachuca near 45.8%% against ESPN BET's 49.2%%. The honest bracket on no-vig CLV is -0.4%% to +7.0%%; clv_novig is set to 0.0 at the conservative end BECAUSE this figure feeds the pre-registered rollback metric, and a metric that can retire a policy should never be flattered. TIER SCOREBOARD: 4 settled, 4-0 on results, mean no-vig CLV ~+0.1%% - still barely above zero after four bets; 11 to the checkpoint. This ticket is money in hand and a neutral process verdict: it is NOT evidence the Liga MX blend works.
A74: 2026-09-04 | B74: Toledo @ Michigan State, CFB Week 1 (8:00 PM ET Fri, Spartan Stadium) | C74: none - market refused | D74: refusal | G74: 0 | H74: validated | I74: 0 | L74: conflict | M74: worked | N74: CONFLICT REFUSAL, engine-fired at -5.25% best-price cross-venue hold. FanDuel's -420 devigs to ~77% Michigan State and KALSHI AGREES at 78c on $79K of volume - but POLYMARKET sits at 83c, five-plus points clear of both. Taking the cheap Toledo side at Polymarket's 17c against Kalshi's MSU 78c is the synthetic-arb shape that has graded wrong three times in this ledger. Note the asymmetry that makes this different from Wednesday's phantom-anchor inversion: there the lone outlier was an unnamed blog board and the exchange was right; here a NAMED book and an exchange agree and the other exchange is the outlier - which is exactly why the hierarchy says refuse rather than pick. Settle records which venue was right. Independent reason to stay away: SP+ has MSU by 13.8 and FPI by 5.4 - a two-touchdown model disagreement on a game with two first-time starting QBs under two new head coaches. || SETTLED - VALIDATED ON PROCESS AND OUTCOME. Michigan State won 30-20 (and did NOT cover -10.5), so the refused Toledo ticket would have LOST outright. The venue ranking against a ~77% closing consensus: FanDuel -420 was dead on (error ~0.0-0.7 points), KALSHI's 78c tracked it within a point, and POLYMARKET's 83c was six points off and NEVER CONVERGED - its market ranged 75-83% across $79K of volume, so the quote we saw sat at the extreme top of its own band. That is the unstable-cross-source signature the refusal rule exists to catch: the apparent six-point edge on Toledo at 17c was venue noise inside an eight-point band, not dispersion. Venue-truth ledger: named books 5, exchange 2. Polymarket stays demoted at 0.45 - nothing here argues otherwise.
A75: 2026-09-09 | B75: Patriots @ Seahawks, NFL Week 1 (8:20 PM ET Wed, Lumen Field) | C75: Patriots ML (road dog) | D75: order_open | E75: 2.7027 | G75: 0 | H75: pending | I75: 0 | L75: degraded | M75: pending | N75: HEADLINE ORDER - dispersion tier (+1.0% bar; Kalshi at 0.45 sharpness sits below the 0.50 fair-line floor, so it is a shop venue, never a fair source). Fires at 37c or better (2.7027, +170). Blended fair 2.675 (37.38%); the model ensemble alone says 39.33%, so a 37c fill is +1.03% on the blend and +6.30% on the model. Best live prices: BetRivers +160 (a fair source, so it carries the +1.5% model-tier bar = 2.715 and misses), Kalshi 39c = 2.5641. TWO BINDING CLAUSES. (1) DRIFT-CANCEL WITH A NAMED TRIGGER: TreVeyon Henderson (NE RB) has not practiced since Aug 24 and his final designation was still outstanding at compile. If New England reaches 37c ON A HENDERSON-OUT HEADLINE, that is a drift, not a fill - the premise our fair was built on changed, the true probability moved down with the price, and we stand down and re-price. A 37c print on ordinary two-way flow with no news is a legitimate standing-above fill. Both graded drift-fills (Liberty Aug-3, Braves Aug-10) arrived exactly this way and both carried negative CLV. (2) BOOK-INTEGRITY FLOOR: the order is void if Kalshi's two legs sum to 100c or less (e.g. NE 36c against SEA 64c). Our own conflict rule refuses a zero/negative synthetic hold on a degraded anchor, and an exchange showing one is showing a stale side, not a gift. Verified at compile: NE 39c + SEA 63c = 102c. PREMISES HELD AT COMPILE: Maye and Darnold both entirely absent from the injury report; NE C Ben Brown OUT. $15 at quarter-Kelly if filled at 37c (returns $41); ~$54 at 36c.
A76: 2026-09-09 | B76: Patriots @ Seahawks, NFL Week 1 - total 44.5 | C76: none - under 44.5 read declined, not priced | D76: refusal | G76: 0 | H76: pending | I76: 0 | L76: degraded | M76: pending | N76: DECLINED READ, registered so it can be graded. Forecast for the 5:20-8:30 PM PT window at open-air Lumen: 20-30 mph gusts across the Puget Sound lowlands strengthening into the evening, plus moderate-to-heavy rain. That is a real under thesis and it is the most confident qualitative statement on this card. It is NOT BET for three independent reasons, any one of which is sufficient: totals never headline (standing rule); FanDuel and BookmakersReview both sit 44.5 -110/-110 with zero cross-venue dispersion, so there is no venue to buy it at; and we carry no calibrated weather model, so any probability we asserted would be invented. The ESPN listing's 45.5 would be the number to buy under if it were real, but it is one-sided and undated. Settle should record whether the game went under 44.5 - if this read keeps grading right while unpriced, that is evidence for building a weather layer, which is a parameter change and needs ledger evidence first.
A78: Blue cells = ledger data (regenerated by sharpods-tracker; edit data/track_record.json, not this sheet). Dashboard recomputes from these rows automatically. To grade a bet you placed yourself: set Type=ticket, Result=won or lost, and fill Stake $ and P&L $ — the Dashboard picks it up. For an order that never filled, set Result=no fill.

Sheet FairLines
A1: Date | B1: Event | C1: Our fair (home) | D1: Close no-vig (home) | E1: Error (pts) | F1: Home won (1/0) | G1: Brier ours | H1: Brier close | I1: Source flag
A2: 2026-07-29 | B2: mlb-2026-07-29-bal-det | C2: 0.6184 | D2: 0.6225 | E2: =ABS(C2-D2)*100 | F2: 0 | G2: =(C2-F2)^2 | H2: =(D2-F2)^2 | I2: clean
A3: 2026-07-29 | B3: mlb-2026-07-29-atl-nym-g1 | C3: 0.4953 | D3: 0.4907 | E3: =ABS(C3-D3)*100 | F3: 1 | G3: =(C3-F3)^2 | H3: =(D3-F3)^2 | I3: clean
A4: 2026-07-29 | B4: mlb-2026-07-29-col-sd | C4: 0.5644 | D4: 0.5617 | E4: =ABS(C4-D4)*100 | F4: 1 | G4: =(C4-F4)^2 | H4: =(D4-F4)^2 | I4: clean
A5: 2026-07-29 | B5: mlb-2026-07-29-tor-wsh | C5: 0.4653 | D5: 0.4678 | E5: =ABS(C5-D5)*100 | F5: 0 | G5: =(C5-F5)^2 | H5: =(D5-F5)^2 | I5: clean
A6: 2026-07-29 | B6: mlb-2026-07-29-phi-mia | C6: 0.4108 | D6: 0.3865 | E6: =ABS(C6-D6)*100 | F6: 1 | G6: =(C6-F6)^2 | H6: =(D6-F6)^2 | I6: clean
A7: 2026-07-30 | B7: mlb-2026-07-30-tex-tb | C7: 0.6203 | D7: 0.5713 | E7: =ABS(C7-D7)*100 | F7: 1 | G7: =(C7-F7)^2 | H7: =(D7-F7)^2 | I7: low-conf close
A8: 2026-07-30 | B8: mlb-2026-07-30-chc-stl | C8: 0.4852 | D8: 0.5233 | E8: =ABS(C8-D8)*100 | F8: 0 | G8: =(C8-F8)^2 | H8: =(D8-F8)^2 | I8: conflict
A9: 2026-07-30 | B9: mlb-2026-07-30-mia-nym | C9: 0.5522 | D9: 0.5454 | E9: =ABS(C9-D9)*100 | F9: 1 | G9: =(C9-F9)^2 | H9: =(D9-F9)^2 | I9: clean
A10: 2026-07-30 | B10: mlb-2026-07-30-wsh-atl | C10: 0.5255 | D10: 0.5665 | E10: =ABS(C10-D10)*100 | F10: 1 | G10: =(C10-F10)^2 | H10: =(D10-F10)^2 | I10: stale quote
A11: 2026-07-30 | B11: mlb-2026-07-30-bos-ath | C11: 0.4117 | D11: 0.3733 | E11: =ABS(C11-D11)*100 | F11: 0 | G11: =(C11-F11)^2 | H11: =(D11-F11)^2 | I11: low-conf close
A12: 2026-07-30 | B12: mlb-2026-07-30-nyy-cws | C12: 0.4317 | D12: 0.5115 | E12: =ABS(C12-D12)*100 | F12: 1 | G12: =(C12-F12)^2 | H12: =(D12-F12)^2 | I12: date trap
A13: 2026-07-30 | B13: mlb-2026-07-30-sea-lad | C13: 0.5883 | D13: 0.5934 | E13: =ABS(C13-D13)*100 | F13: 1 | G13: =(C13-F13)^2 | H13: =(D13-F13)^2 | I13: clean
... A228: 2026-09-04 | B228: wta-2026-09-04-svi-kal | C228: 0.2874 | D228: 0.2816 | E228: =ABS(C228-D228)*100 | F228: 1 | G228: =(C228-F228)^2 | H228: =(D228-F228)^2 | I228: clean

Sheet Dashboard
A1: SharpOds Tracker — Dashboard
A2: Every value below is a formula over Bets/FairLines: add or settle rows there and this sheet recomputes.
A5: Tickets settled | B5: =COUNTIFS(Bets!D:D,"ticket",Bets!H:H,"<>pending")
A6: Ticket wins | B6: =COUNTIFS(Bets!D:D,"ticket",Bets!H:H,"won")
A7: Win rate | B7: =IFERROR(B6/B5,0)
A8: Total staked | B8: =SUMIFS(Bets!G:G,Bets!D:D,"ticket",Bets!H:H,"<>pending")
A9: Net P&L | B9: =SUM(Bets!I:I)
A10: ROI on stakes | B10: =IFERROR(B9/B8,0)
A11: Mean CLV (no-vig), tickets | B11: =IFERROR(AVERAGEIFS(Bets!K:K,Bets!D:D,"ticket"),0)
A12: Limit orders unfilled | B12: =COUNTIF(Bets!D:D,"order_unfilled")
A13: Open orders / pending | B13: =COUNTIF(Bets!H:H,"pending")
A14: Decisions settled | B14: =COUNTIF(Bets!M:M,"worked")+COUNTIF(Bets!M:M,"miss")
A15: Process validated (worked) | B15: =COUNTIF(Bets!M:M,"worked")
A16: Process misses | B16: =COUNTIF(Bets!M:M,"miss")
A17: Fair lines graded | B17: =COUNT(FairLines!E:E)
A18: Mean |fair − close| (pts) | B18: =IFERROR(AVERAGE(FairLines!E:E),0)
A19: Max |fair − close| (pts) | B19: =IFERROR(MAX(FairLines!E:E),0)
A20: Clean-source mean error (pts) | B20: =IFERROR(AVERAGEIFS(FairLines!E:E,FairLines!I:I,"clean"),0)
A21: Flagged-source mean error (pts) | B21: =IFERROR(AVERAGEIFS(FairLines!E:E,FairLines!I:I,"<>clean"),0)
A22: Brier — SharpOds fair | B22: =IFERROR(AVERAGE(FairLines!G:G),0)
A23: Brier — closing line | B23: =IFERROR(AVERAGE(FairLines!H:H),0)
A24: Brier — coin flip (reference) | B24: =0.25
A27: What worked / what didn't (from the decision log)
A28: [WORKED] Full 5-game slate: Favorites went 2-3; both most-likely sides blew 6+ run leads; every listed price was -EV vs fair (avg -3.3%). Passing saved money.
A29: [WORKED] BAL @ DET: Line closed 1.56-1.59, moving away; discipline held. Tigers lost 9-10 in 12 - a chased fill would have lost.
A30: [WORKED] CHC @ STL: Labeled unverified staleness and not executed; the close proved it was quote drift, not free money.
A31: [WORKED] NYY @ CHC: Close CHC -140 landed on the sportsbook consensus; Polymarket 52c was the stale outlier (NYY won 2-0 as a +130 dog - vs the close that bet was -7% EV luck). Refusal correct.
A32: [WORKED] PHI @ BAL: PHI never traded above 2.06 (target 2.10). Close no-vig PHI 0.467: even at target the bet was -2% vs close - not filling saved money. SportsGrid model lean (PHI 54%) was the wrong side per the close.
A33: [WORKED] PIT @ CIN: PIT -120 to -136 all day, never near the 1.966 target. Close no-vig PIT 0.564: a 1.966 fill would have been ~+11% EV vs close - right side, market never paid the price.
A34: [WORKED] PIT @ CIN: CIN never traded above +106 (2.06) - 17 cents short of the 2.231 bar; the '+120 one source' quote was never corroborated. CIN lost 1-4, so no fill dodged a loss; vs the no-vig close a 2.231 fill would still have been +EV (right side, market never paid).
A35: [WORKED] NYY @ CHC: Refusal correct, with a twist: the close landed NYY road-favorite (-122 to -132; CHC +102/+105) - the OPPOSITE of our 'books CHC 1.62' quote, which no closing book corroborates. That quote was stale/wrong (flagged for provenance). Polymarket NYY 54c was actually the consensus side. CHC won 5-2 anyway - neither side's value story survived. Conflict rule worked for the right reason: garbage inputs were refused, not priced.
A36: [WORKED] WSH @ ATL: Braves 8-3. Polymarket-only board stayed unpriced per the 0.45-sharpness demotion; no book close collected for this game.
A37: [WORKED] PHI @ BAL: Fill ambiguous: consensus close +119 (2.19) never reached the 2.225 bar, but SportsGrid reported 'BAL +125 at other books' pregame, which would have filled. Graded no-fill on the consensus board we price from. BAL lost 0-5, so neither grading forfeits a win; a phantom fill would have lost. Single-book-anchor caveat from pre-registration stands.
A38: [WORKED] SEA @ POR (MLS): NO BET - user report (the only fill oracle; pages 403 post-hoc): the prediction-market ask had moved above the 45c stand-down line (engine minimum 2.23) by bet time, so per the slip's own fill rule the order did not fire. Paper grade of the 2.273 listed snapshot: Portland won 2-1 and the number beat the bet365 close 2.05/3.80/3.00 by +10.9% raw / +4.5% no-vig - the edge was real at the snapshot, and it decayed before execution. Standing down was correct: at the moved ask the +2.5% EV bar was no longer met.
... A98: Source: data/track_record.json (SharpOds ledger); regenerated by `sharpods-tracker`. Assumption: closing lines are best-available day-of published numbers, not exchange-verified closing ticks.
